odoo/addons/invader_payment_paypal/README.rst
odoo/addons/invader_payment_paypal/__init__.py
odoo/addons/invader_payment_paypal/__manifest__.py
odoo/addons/invader_payment_paypal/i18n/invader_payment_paypal.pot
odoo/addons/invader_payment_paypal/models/__init__.py
odoo/addons/invader_payment_paypal/models/payment_acquirer.py
odoo/addons/invader_payment_paypal/readme/CONTRIBUTORS.rst
odoo/addons/invader_payment_paypal/readme/DESCRIPTION.rst
odoo/addons/invader_payment_paypal/services/__init__.py
odoo/addons/invader_payment_paypal/services/payment_paypal.py
odoo/addons/invader_payment_paypal/static/description/index.html
odoo/addons/invader_payment_paypal/views/payment_acquirer_view.xml
odoo13_addon_invader_payment_paypal-13.0.1.0.1.dist-info/METADATA
odoo13_addon_invader_payment_paypal-13.0.1.0.1.dist-info/WHEEL
odoo13_addon_invader_payment_paypal-13.0.1.0.1.dist-info/top_level.txt
odoo13_addon_invader_payment_paypal-13.0.1.0.1.dist-info/RECORD
